<?xml version="1.0" encoding="UTF-8"?>
<!DOCTYPE mapper PUBLIC "-//mybatis.org//DTD Mapper 3.0//EN" "http://mybatis.org/dtd/mybatis-3-mapper.dtd">
<mapper namespace="com.alibaba.aecp.aecpsrvcenter.mapper.generated.aecpsrvcenter10000.ChangeVersionMapper">
    <resultMap id="BaseResultMap" type="model.aecpsrvcenter10000.ChangeVersion">
        <!--
          WARNING - @mbg.generated
          This element is automatically generated by MyBatis Generator, do not modify.
          This element was generated on Thu Jun 06 11:32:10 CST 2019.
        -->
        <id column="id" jdbcType="BIGINT" property="id"/>
        <result column="gmt_create" jdbcType="TIMESTAMP" property="gmtCreate"/>
        <result column="gmt_modified" jdbcType="TIMESTAMP" property="gmtModified"/>
        <result column="domain_code" jdbcType="VARCHAR" property="domainCode"/>
        <result column="tenant_id" jdbcType="BIGINT" property="tenantId"/>
        <result column="creator" jdbcType="VARCHAR" property="creator"/>
        <result column="modifier" jdbcType="VARCHAR" property="modifier"/>
        <result column="is_deleted" jdbcType="CHAR" property="isDeleted"/>
        <result column="mdc_ext" jdbcType="VARCHAR" property="mdcExt"/>
        <result column="change_id" jdbcType="VARCHAR" property="changeId"/>
        <result column="app_code" jdbcType="VARCHAR" property="appCode"/>
        <result column="version_uuid" jdbcType="VARCHAR" property="versionUuid"/>
    </resultMap>
    <sql id="Base_Column_List">
        <!--
          WARNING - @mbg.generated
          This element is automatically generated by MyBatis Generator, do not modify.
          This element was generated on Thu Jun 06 11:32:10 CST 2019.
        -->
        id, gmt_create, gmt_modified, domain_code, tenant_id, creator, modifier, is_deleted,
        mdc_ext, change_id, app_code, version_uuid
    </sql>
    <select id="selectByPrimaryKey" parameterType="java.lang.Long" resultMap="BaseResultMap">
        <!--
          WARNING - @mbg.generated
          This element is automatically generated by MyBatis Generator, do not modify.
          This element was generated on Thu Jun 06 11:32:10 CST 2019.
        -->
        select
        <include refid="Base_Column_List"/>
        from aecpsrvcenter10000.change_version
        where id = #{id,jdbcType=BIGINT}
    </select>
    <delete id="deleteByPrimaryKey" parameterType="java.lang.Long">
        <!--
          WARNING - @mbg.generated
          This element is automatically generated by MyBatis Generator, do not modify.
          This element was generated on Thu Jun 06 11:32:10 CST 2019.
        -->
        delete from aecpsrvcenter10000.change_version
        where id = #{id,jdbcType=BIGINT}
    </delete>
    <insert id="insert" parameterType="model.aecpsrvcenter10000.ChangeVersion">
        <!--
          WARNING - @mbg.generated
          This element is automatically generated by MyBatis Generator, do not modify.
          This element was generated on Thu Jun 06 11:32:10 CST 2019.
        -->
        insert into aecpsrvcenter10000.change_version (id, gmt_create, gmt_modified,
        domain_code, tenant_id, creator,
        modifier, is_deleted, mdc_ext,
        change_id, app_code, version_uuid
        )
        values (#{id,jdbcType=BIGINT}, #{gmtCreate,jdbcType=TIMESTAMP}, #{gmtModified,jdbcType=TIMESTAMP},
        #{domainCode,jdbcType=VARCHAR}, #{tenantId,jdbcType=BIGINT}, #{creator,jdbcType=VARCHAR},
        #{modifier,jdbcType=VARCHAR}, #{isDeleted,jdbcType=CHAR}, #{mdcExt,jdbcType=VARCHAR},
        #{changeId,jdbcType=VARCHAR}, #{appCode,jdbcType=VARCHAR}, #{versionUuid,jdbcType=VARCHAR}
        )
    </insert>
    <insert id="insertSelective" parameterType="model.aecpsrvcenter10000.ChangeVersion">
        <!--
          WARNING - @mbg.generated
          This element is automatically generated by MyBatis Generator, do not modify.
          This element was generated on Thu Jun 06 11:32:10 CST 2019.
        -->
        insert into aecpsrvcenter10000.change_version
        <trim prefix="(" suffix=")" suffixOverrides=",">
            <if test="id != null">
                id,
            </if>
            <if test="gmtCreate != null">
                gmt_create,
            </if>
            <if test="gmtModified != null">
                gmt_modified,
            </if>
            <if test="domainCode != null">
                domain_code,
            </if>
            <if test="tenantId != null">
                tenant_id,
            </if>
            <if test="creator != null">
                creator,
            </if>
            <if test="modifier != null">
                modifier,
            </if>
            <if test="isDeleted != null">
                is_deleted,
            </if>
            <if test="mdcExt != null">
                mdc_ext,
            </if>
            <if test="changeId != null">
                change_id,
            </if>
            <if test="appCode != null">
                app_code,
            </if>
            <if test="versionUuid != null">
                version_uuid,
            </if>
        </trim>
        <trim prefix="values (" suffix=")" suffixOverrides=",">
            <if test="id != null">
                #{id,jdbcType=BIGINT},
            </if>
            <if test="gmtCreate != null">
                #{gmtCreate,jdbcType=TIMESTAMP},
            </if>
            <if test="gmtModified != null">
                #{gmtModified,jdbcType=TIMESTAMP},
            </if>
            <if test="domainCode != null">
                #{domainCode,jdbcType=VARCHAR},
            </if>
            <if test="tenantId != null">
                #{tenantId,jdbcType=BIGINT},
            </if>
            <if test="creator != null">
                #{creator,jdbcType=VARCHAR},
            </if>
            <if test="modifier != null">
                #{modifier,jdbcType=VARCHAR},
            </if>
            <if test="isDeleted != null">
                #{isDeleted,jdbcType=CHAR},
            </if>
            <if test="mdcExt != null">
                #{mdcExt,jdbcType=VARCHAR},
            </if>
            <if test="changeId != null">
                #{changeId,jdbcType=VARCHAR},
            </if>
            <if test="appCode != null">
                #{appCode,jdbcType=VARCHAR},
            </if>
            <if test="versionUuid != null">
                #{versionUuid,jdbcType=VARCHAR},
            </if>
        </trim>
    </insert>
    <update id="updateByPrimaryKeySelective" parameterType="model.aecpsrvcenter10000.ChangeVersion">
        <!--
          WARNING - @mbg.generated
          This element is automatically generated by MyBatis Generator, do not modify.
          This element was generated on Thu Jun 06 11:32:10 CST 2019.
        -->
        update aecpsrvcenter10000.change_version
        <set>
            <if test="gmtCreate != null">
                gmt_create = #{gmtCreate,jdbcType=TIMESTAMP},
            </if>
            <if test="gmtModified != null">
                gmt_modified = #{gmtModified,jdbcType=TIMESTAMP},
            </if>
            <if test="domainCode != null">
                domain_code = #{domainCode,jdbcType=VARCHAR},
            </if>
            <if test="tenantId != null">
                tenant_id = #{tenantId,jdbcType=BIGINT},
            </if>
            <if test="creator != null">
                creator = #{creator,jdbcType=VARCHAR},
            </if>
            <if test="modifier != null">
                modifier = #{modifier,jdbcType=VARCHAR},
            </if>
            <if test="isDeleted != null">
                is_deleted = #{isDeleted,jdbcType=CHAR},
            </if>
            <if test="mdcExt != null">
                mdc_ext = #{mdcExt,jdbcType=VARCHAR},
            </if>
            <if test="changeId != null">
                change_id = #{changeId,jdbcType=VARCHAR},
            </if>
            <if test="appCode != null">
                app_code = #{appCode,jdbcType=VARCHAR},
            </if>
            <if test="versionUuid != null">
                version_uuid = #{versionUuid,jdbcType=VARCHAR},
            </if>
        </set>
        where id = #{id,jdbcType=BIGINT}
    </update>
    <update id="updateByPrimaryKey" parameterType="model.aecpsrvcenter10000.ChangeVersion">
        <!--
          WARNING - @mbg.generated
          This element is automatically generated by MyBatis Generator, do not modify.
          This element was generated on Thu Jun 06 11:32:10 CST 2019.
        -->
        update aecpsrvcenter10000.change_version
        set gmt_create = #{gmtCreate,jdbcType=TIMESTAMP},
        gmt_modified = #{gmtModified,jdbcType=TIMESTAMP},
        domain_code = #{domainCode,jdbcType=VARCHAR},
        tenant_id = #{tenantId,jdbcType=BIGINT},
        creator = #{creator,jdbcType=VARCHAR},
        modifier = #{modifier,jdbcType=VARCHAR},
        is_deleted = #{isDeleted,jdbcType=CHAR},
        mdc_ext = #{mdcExt,jdbcType=VARCHAR},
        change_id = #{changeId,jdbcType=VARCHAR},
        app_code = #{appCode,jdbcType=VARCHAR},
        version_uuid = #{versionUuid,jdbcType=VARCHAR}
        where id = #{id,jdbcType=BIGINT}
    </update>

    <!--auto generated by MybatisCodeHelper on 2019-06-06-->
    <update id="updateisDeletedByChangeIdAndAppCode">
	update aecpsrvcenter10000.change_version
	set is_deleted=#{updatedIsDeleted,jdbcType=CHAR}
	where change_id=#{changeId,jdbcType=VARCHAR} and app_code=#{appCode,jdbcType=VARCHAR}</update>

    <!--auto generated by MybatisCodeHelper on 2019-06-06-->
    <select id="findByAll" resultMap="BaseResultMap">
        select
        <include refid="Base_Column_List"/>
        from aecpsrvcenter10000.change_version
        where 1=1
        <if test="id!=null">
            and id=#{id,jdbcType=BIGINT}
        </if>
        <if test="gmtCreate!=null">
            and gmt_create=#{gmtCreate,jdbcType=TIMESTAMP}
        </if>
        <if test="gmtModified!=null">
            and gmt_modified=#{gmtModified,jdbcType=TIMESTAMP}
        </if>
        <if test="domainCode!=null">
            and domain_code=#{domainCode,jdbcType=VARCHAR}
        </if>
        <if test="tenantId!=null">
            and tenant_id=#{tenantId,jdbcType=BIGINT}
        </if>
        <if test="creator!=null">
            and creator=#{creator,jdbcType=VARCHAR}
        </if>
        <if test="modifier!=null">
            and modifier=#{modifier,jdbcType=VARCHAR}
        </if>
        <if test="isDeleted != null and isDeleted != ''">
            and is_deleted=#{isDeleted,jdbcType=CHAR}
        </if>
        <if test="mdcExt!=null">
            and mdc_ext=#{mdcExt,jdbcType=VARCHAR}
        </if>
        <if test="changeId != null and changeId != ''">
            and change_id=#{changeId,jdbcType=VARCHAR}
        </if>
        <if test="appCode != null and appCode != ''">
            and app_code=#{appCode,jdbcType=VARCHAR}
        </if>
        <if test="versionUuid != null and versionUuid != ''">
            and version_uuid=#{versionUuid,jdbcType=VARCHAR}
        </if>
    </select>
</mapper>